vpem/__init__.py
vpem/__main__.py
vpem/apply_groups.py
vpem/categorize_extensions.py
vpem/create_extensions_table.py
vpem/load_extension_groups.py
vpem/main.py
vpem/py.typed
vpem/result_with_err.py
vpem/save_extension_groups.py
vpem/update_extensions_from_profile.py
vpem/vscode/__init__.py
vpem/vscode/extension_details.py
vpem/vscode/install_vscode_extensions.py
vpem/vscode/list_installed_vscode_extensions.py
vpem/vscode/load_all_extension_details.py
vpem/vscode/retrieve_vscode_ext_details.py
vpem/vscode/save_all_extension_details.py
vpem/vscode/uninstall_vscode_extensions.py
vscode_profile_extension_manager-0.1.13.dist-info/LICENSE
vscode_profile_extension_manager-0.1.13.dist-info/METADATA
vscode_profile_extension_manager-0.1.13.dist-info/WHEEL
vscode_profile_extension_manager-0.1.13.dist-info/entry_points.txt
vscode_profile_extension_manager-0.1.13.dist-info/top_level.txt
vscode_profile_extension_manager-0.1.13.dist-info/RECORD
