Metadata-Version: 2.1
Name: vscode_profile_extension_manager
Version: 0.1.13
Summary: Effortlessly manage your vscode extenstions in each profile
Author-email: Mike Crowe <drmikecrowe@gmail.com>
License: Apache License
Project-URL: Homepage, https://github.com/drmikecrowe/vscode-profile-extension-manager
Project-URL: Repository, https://github.com/drmikecrowe/vscode-profile-extension-manager.git
Classifier: Development Status :: 3 - Alpha
Classifier: Intended Audience :: Developers
Classifier: Topic :: Software Development :: Build Tools
Requires-Python: <3.14,>=3.11
License-File: LICENSE
Requires-Dist: rich >=13.8.1
Requires-Dist: textual >=0.81.0
Requires-Dist: click >=8.1.7
Requires-Dist: requests >=2.32.3
Requires-Dist: prodict >=0.8.18
Requires-Dist: inquirer >=3.4.0
Requires-Dist: pyinstaller >=6.10.0
Requires-Dist: appdirs >=1.4.4
Provides-Extra: dev
Requires-Dist: build <2,>=1.2.1 ; extra == 'dev'
Requires-Dist: pyinstaller <7,>=6.4.0 ; extra == 'dev'
Requires-Dist: pyinstaller-versionfile <3,>=2.1.1 ; extra == 'dev'
